[
  {
    "id": 1,
    "category": "Inspiration",
    "quote": "The only way to do great work is to love what you do.",
    "author": "Steve Jobs",
    "description": "Encouraging quote about the importance of passion in work."
  },
  {
    "id": 2,
    "category": "Life",
    "quote": "Life is what happens when you're busy making other plans.",
    "author": "John Lennon",
    "description": "A reminder to appreciate the present moment."
  },
  {
    "id": 3,
    "category": "Motivation",
    "quote": "Success is not final, failure is not fatal: It is the courage to continue that counts.",
    "author": "Winston Churchill",
    "description": "Motivational quote about the importance of perseverance."
  },
  {
    "id": 4,
    "category": "Wisdom",
    "quote": "The only true wisdom is in knowing you know nothing.",
    "author": "Socrates",
    "description": "Philosophical insight about the nature of wisdom."
  },
  {
    "id": 5,
    "category": "Love",
    "quote": "The greatest happiness you can have is knowing that you do not necessarily require happiness.",
    "author": "William Saroyan",
    "description": "A unique perspective on the pursuit of happiness."
  },
  {
    "id": 6,
    "category": "Technology",
    "quote": "Any sufficiently advanced technology is indistinguishable from magic.",
    "author": "Arthur C. Clarke",
    "description": "Thoughts on the magical nature of advanced technology."
  },
  {
    "id": 7,
    "category": "Creativity",
    "quote": "Creativity is intelligence having fun.",
    "author": "Albert Einstein",
    "description": "A playful definition of the relationship between creativity and intelligence."
  },
  {
    "id": 8,
    "category": "Courage",
    "quote": "It takes a great deal of bravery to stand up to our enemies, but just as much to stand up to our friends.",
    "author": "J.K. Rowling",
    "description": "Reflection on the different forms of courage."
  },
  {
    "id": 9,
    "category": "Nature",
    "quote": "Look deep into nature, and then you will understand everything better.",
    "author": "Albert Einstein",
    "description": "Insight into the profound understanding that nature can offer."
  },
  {
    "id": 10,
    "category": "Change",
    "quote": "Be the change that you wish to see in the world.",
    "author": "Mahatma Gandhi",
    "description": "A call to action for individuals to initiate positive change."
  },
  {
    "id": 11,
    "category": "Wisdom",
    "quote": "Wisdom is the reward you get for a lifetime of listening when you'd have preferred to talk.",
    "author": "Doug Larson",
    "description": "Reflection on the value of listening and learning throughout life."
  },
  {
    "id": 12,
    "category": "Perseverance",
    "quote": "It's not whether you get knocked down, it's whether you get up.",
    "author": "Vince Lombardi",
    "description": "Encouragement to persevere and overcome challenges."
  },
  {
    "id": 13,
    "category": "Success",
    "quote": "Success usually comes to those who are too busy to be looking for it.",
    "author": "Henry David Thoreau",
    "description": "A perspective on the relationship between busyness and success."
  },
  {
    "id": 14,
    "category": "Friendship",
    "quote": "Friendship is born at that moment when one person says to another, 'What! You too? I thought I was the only one.'",
    "author": "C.S. Lewis",
    "description": "Definition of the special bond created by shared experiences."
  },
  {
    "id": 15,
    "category": "Imagination",
    "quote": "Imagination is more important than knowledge. For knowledge is limited, whereas imagination embraces the entire world, stimulating progress, giving birth to evolution.",
    "author": "Albert Einstein",
    "description": "Einstein's perspective on the power of imagination in shaping the future."
  },
  {
    "id": 16,
    "category": "Courage",
    "quote": "Courage is resistance to fear, mastery of fear—not absence of fear.",
    "author": "Mark Twain",
    "description": "An insightful take on the nature of courage and fear."
  },
  {
    "id": 17,
    "category": "Hope",
    "quote": "Hope is the thing with feathers that perches in the soul and sings the tune without the words and never stops at all.",
    "author": "Emily Dickinson",
    "description": "A poetic expression of the enduring nature of hope."
  },
  {
    "id": 18,
    "category": "Adventure",
    "quote": "Life is either a daring adventure or nothing at all.",
    "author": "Helen Keller",
    "description": "An invitation to embrace life with a spirit of adventure and courage."
  },
  {
    "id": 19,
    "category": "Knowledge",
    "quote": "The more that you read, the more things you will know. The more that you learn, the more places you'll go.",
    "author": "Dr. Seuss",
    "description": "Encouragement to pursue knowledge and the doors it opens."
  },
  {
    "id": 20,
    "category": "Humor",
    "quote": "The secret of life, though, is to fall seven times and to get up eight times.",
    "author": "Paulo Coelho",
    "description": "A humorous take on resilience and the essence of life."
  },
  {
    "id": 21,
    "category": "Dreams",
    "quote": "The future belongs to those who believe in the beauty of their dreams.",
    "author": "Eleanor Roosevelt",
    "description": "A motivational quote about the power of believing in one's dreams."
  },
  {
    "id": 22,
    "category": "Happiness",
    "quote": "Happiness is not something ready-made. It comes from your own actions.",
    "author": "Dalai Lama",
    "description": "Insight into the role of personal actions in the pursuit of happiness."
  },
  {
    "id": 23,
    "category": "Adventure",
    "quote": "Adventure is worthwhile in itself.",
    "author": "Amelia Earhart",
    "description": "An adventurer's perspective on the intrinsic value of exploration."
  },
  {
    "id": 24,
    "category": "Wisdom",
    "quote": "Knowledge speaks, but wisdom listens.",
    "author": "Jimi Hendrix",
    "description": "A musical take on the difference between knowledge and wisdom."
  },
  {
    "id": 25,
    "category": "Love",
    "quote": "The best thing to hold onto in life is each other.",
    "author": "Audrey Hepburn",
    "description": "A beautiful sentiment about the importance of human connections."
  },
  {
    "id": 26,
    "category": "Imagination",
    "quote": "Imagination is the beginning of creation. You imagine what you desire, you will what you imagine, and at last, you create what you will.",
    "author": "George Bernard Shaw",
    "description": "A profound exploration of the creative process and imagination."
  },
  {
    "id": 27,
    "category": "Optimism",
    "quote": "The pessimist complains about the wind; the optimist expects it to change; the realist adjusts the sails.",
    "author": "William Arthur Ward",
    "description": "Different perspectives on approaching challenges and change."
  },
  {
    "id": 28,
    "category": "Perseverance",
    "quote": "Perseverance is not a long race; it's many short races one after another.",
    "author": "Walter Elliot",
    "description": "A metaphorical view on the nature of perseverance and endurance."
  },
  {
    "id": 29,
    "category": "Leadership",
    "quote": "A good leader takes a little more than his share of the blame, a little less than his share of the credit.",
    "author": "Arnold H. Glasow",
    "description": "A reflection on the responsibilities of leadership and accountability."
  },
  {
    "id": 30,
    "category": "Curiosity",
    "quote": "I have no special talents. I am only passionately curious.",
    "author": "Albert Einstein",
    "description": "Einstein's acknowledgment of the power of curiosity in intellectual pursuits."
  },
  {
    "id": 31,
    "category": "Success",
    "quote": "Success is stumbling from failure to failure with no loss of enthusiasm.",
    "author": "Winston S. Churchill",
    "description": "An optimistic perspective on the journey to success and learning from failures."
  },
  {
    "id": 32,
    "category": "Life",
    "quote": "Life is either a daring adventure or nothing at all.",
    "author": "Helen Keller",
    "description": "An invitation to embrace life with a spirit of adventure and courage."
  },
  {
    "id": 33,
    "category": "Wisdom",
    "quote": "It is not that I'm so smart. But I stay with the questions much longer.",
    "author": "Albert Einstein",
    "description": "Insight into the importance of staying curious and engaged with questions."
  },
  {
    "id": 34,
    "category": "Optimism",
    "quote": "The only limit to our realization of tomorrow will be our doubts of today.",
    "author": "Franklin D. Roosevelt",
    "description": "A reflection on the impact of doubts on future achievements."
  },
  {
    "id": 35,
    "category": "Creativity",
    "quote": "Creativity is contagious, pass it on.",
    "author": "Albert Einstein",
    "description": "Encouragement to share and inspire creativity in others."
  },
  {
    "id": 36,
    "category": "Friendship",
    "quote": "Friendship is the only cement that will ever hold the world together.",
    "author": "Woodrow Wilson",
    "description": "A poetic perspective on the unifying power of friendship."
  },
  {
    "id": 37,
    "category": "Change",
    "quote": "Change your thoughts and you change your world.",
    "author": "Norman Vincent Peale",
    "description": "Insight into the transformative power of positive thinking."
  },
  {
    "id": 38,
    "category": "Love",
    "quote": "To love and be loved is to feel the sun from both sides.",
    "author": "David Viscott",
    "description": "A metaphorical expression of the warmth and reciprocity of love."
  },
  {
    "id": 39,
    "category": "Persistence",
    "quote": "The difference between a successful person and others is not a lack of strength, not a lack of knowledge, but rather a lack in will.",
    "author": "Vince Lombardi",
    "description": "A reflection on the role of determination and willpower in success."
  },
  {
    "id": 40,
    "category": "Wisdom",
    "quote": "Wisdom begins in wonder.",
    "author": "Socrates",
    "description": "A concise perspective on the origin of wisdom and the importance of curiosity."
  },
  {
    "id": 41,
    "category": "Motivation",
    "quote": "The only way to achieve the impossible is to believe it is possible.",
    "author": "Charles Kingsleigh (Alice in Wonderland)",
    "description": "A motivational quote from the fictional character Charles Kingsleigh in Alice in Wonderland."
  },
  {
    "id": 42,
    "category": "Success",
    "quote": "Success is not the key to happiness. Happiness is the key to success. If you love what you are doing, you will be successful.",
    "author": "Albert Schweitzer",
    "description": "An insightful perspective on the relationship between happiness and success."
  },
  {
    "id": 43,
    "category": "Perseverance",
    "quote": "Perseverance is not a sprint; it's a marathon of one foot in front of the other.",
    "author": "Bonnie St. John",
    "description": "A metaphorical view on the enduring nature of perseverance."
  },
  {
    "id": 44,
    "category": "Change",
    "quote": "Change is the law of life. And those who look only to the past or present are certain to miss the future.",
    "author": "John F. Kennedy",
    "description": "Reflection on the inevitability of change and the importance of adapting to it."
  },
  {
    "id": 45,
    "category": "Love",
    "quote": "Love is that condition in which the happiness of another person is essential to your own.",
    "author": "Robert A. Heinlein",
    "description": "A profound definition of the selfless nature of love."
  },
  {
    "id": 46,
    "category": "Wisdom",
    "quote": "Knowledge is having the right answer. Intelligence is asking the right question.",
    "author": "Unknown",
    "description": "A thought-provoking distinction between knowledge and intelligence."
  },
  {
    "id": 47,
    "category": "Hope",
    "quote": "Hope is important because it can make the present moment less difficult to bear. If we believe that tomorrow will be better, we can bear a hardship today.",
    "author": "Thich Nhat Hanh",
    "description": "A Buddhist perspective on the significance of hope in facing challenges."
  },
  {
    "id": 48,
    "category": "Friendship",
    "quote": "A friend is someone who knows all about you and still loves you.",
    "author": "Elbert Hubbard",
    "description": "A warm definition of the depth of true friendship."
  },
  {
    "id": 49,
    "category": "Courage",
    "quote": "Courage is not the absence of fear, but rather the assessment that something else is more important than fear.",
    "author": "Franklin D. Roosevelt",
    "description": "A nuanced perspective on the relationship between courage and fear."
  },
  {
    "id": 50,
    "category": "Wisdom",
    "quote": "The true sign of intelligence is not knowledge but imagination.",
    "author": "Albert Einstein",
    "description": "Einstein's viewpoint on the role of imagination in measuring intelligence."
  },
  {
    "id": 51,
    "category": "Success",
    "quote": "Success is not final, failure is not fatal: It is the courage to continue that counts.",
    "author": "Winston Churchill",
    "description": "A timeless reflection on the nature of success and courage in the face of challenges."
  },
  {
    "id": 52,
    "category": "Inspiration",
    "quote": "The only way to do great work is to love what you do.",
    "author": "Steve Jobs",
    "description": "An inspiring quote emphasizing the importance of passion in one's work."
  },
  {
    "id": 53,
    "category": "Life",
    "quote": "Life is what happens when you're busy making other plans.",
    "author": "John Lennon",
    "description": "A reminder to cherish the present moment amidst life's plans and uncertainties."
  },
  {
    "id": 54,
    "category": "Wisdom",
    "quote": "The only true wisdom is in knowing you know nothing.",
    "author": "Socrates",
    "description": "A philosophical insight into the nature of true wisdom and humility."
  },
  {
    "id": 55,
    "category": "Love",
    "quote": "The greatest happiness you can have is knowing that you do not necessarily require happiness.",
    "author": "William Saroyan",
    "description": "A unique perspective on finding happiness in not necessarily seeking it."
  },
  {
    "id": 56,
    "category": "Technology",
    "quote": "Any sufficiently advanced technology is indistinguishable from magic.",
    "author": "Arthur C. Clarke",
    "description": "A thought-provoking comparison between advanced technology and magic."
  },
  {
    "id": 57,
    "category": "Creativity",
    "quote": "Creativity is intelligence having fun.",
    "author": "Albert Einstein",
    "description": "A playful definition of the relationship between creativity and intelligence."
  },
  {
    "id": 58,
    "category": "Courage",
    "quote": "It takes a great deal of bravery to stand up to our enemies, but just as much to stand up to our friends.",
    "author": "J.K. Rowling",
    "description": "Reflection on the various forms of courage, both in confrontation and support."
  },
  {
    "id": 59,
    "category": "Nature",
    "quote": "Look deep into nature, and then you will understand everything better.",
    "author": "Albert Einstein",
    "description": "Insight into the profound understanding that nature can offer about life and existence."
  },
  {
    "id": 60,
    "category": "Change",
    "quote": "Be the change that you wish to see in the world.",
    "author": "Mahatma Gandhi",
    "description": "A call to action for individuals to initiate positive change in the world."
  },
  {
    "id": 61,
    "category": "Inspiration",
    "quote": "The best way to predict the future is to create it.",
    "author": "Peter Drucker",
    "description": "An empowering quote encouraging proactive efforts in shaping one's future."
  },
  {
    "id": 62,
    "category": "Leadership",
    "quote": "A leader is one who knows the way, goes the way, and shows the way.",
    "author": "John C. Maxwell",
    "description": "A concise definition of leadership emphasizing knowledge, action, and guidance."
  },
  {
    "id": 63,
    "category": "Wisdom",
    "quote": "Knowing others is intelligence; knowing yourself is true wisdom. Mastering others is strength; mastering yourself is true power.",
    "author": "Lao Tzu",
    "description": "Insight into the facets of intelligence, wisdom, strength, and true power."
  },
  {
    "id": 64,
    "category": "Happiness",
    "quote": "The greatest happiness you can give is to be unwaveringly loyal to what you believe in.",
    "author": "Julie Donner Andersen",
    "description": "A perspective on the joy derived from unwavering loyalty to one's beliefs."
  },
  {
    "id": 65,
    "category": "Perseverance",
    "quote": "Success is not final, failure is not fatal: It is the courage to continue that counts.",
    "author": "Winston Churchill",
    "description": "A timeless reflection on the nature of success and courage in the face of challenges."
  },
  {
    "id": 66,
    "category": "Imagination",
    "quote": "The true sign of intelligence is not knowledge but imagination.",
    "author": "Albert Einstein",
    "description": "Einstein's viewpoint on the role of imagination in measuring intelligence."
  },
  {
    "id": 67,
    "category": "Hope",
    "quote": "Hope is important because it can make the present moment less difficult to bear. If we believe that tomorrow will be better, we can bear a hardship today.",
    "author": "Thich Nhat Hanh",
    "description": "A Buddhist perspective on the significance of hope in facing challenges."
  },
  {
    "id": 68,
    "category": "Friendship",
    "quote": "A friend is someone who knows all about you and still loves you.",
    "author": "Elbert Hubbard",
    "description": "A warm definition of the depth of true friendship."
  },
  {
    "id": 69,
    "category": "Courage",
    "quote": "Courage is not the absence of fear, but rather the assessment that something else is more important than fear.",
    "author": "Franklin D. Roosevelt",
    "description": "A nuanced perspective on the relationship between courage and fear."
  },
  {
    "id": 70,
    "category": "Wisdom",
    "quote": "Wisdom begins in wonder.",
    "author": "Socrates",
    "description": "A concise perspective on the origin of wisdom and the importance of curiosity."
  },
  {
    "id": 71,
    "category": "Motivation",
    "quote": "The only way to do great work is to love what you do.",
    "author": "Steve Jobs",
    "description": "An inspiring quote emphasizing the importance of passion in one's work."
  },
  {
    "id": 72,
    "category": "Life",
    "quote": "Life is what happens when you're busy making other plans.",
    "author": "John Lennon",
    "description": "A reminder to cherish the present moment amidst life's plans and uncertainties."
  },
  {
    "id": 73,
    "category": "Wisdom",
    "quote": "The only true wisdom is in knowing you know nothing.",
    "author": "Socrates",
    "description": "A philosophical insight into the nature of true wisdom and humility."
  },
  {
    "id": 74,
    "category": "Love",
    "quote": "The greatest happiness you can have is knowing that you do not necessarily require happiness.",
    "author": "William Saroyan",
    "description": "A unique perspective on finding happiness in not necessarily seeking it."
  },
  {
    "id": 75,
    "category": "Technology",
    "quote": "Any sufficiently advanced technology is indistinguishable from magic.",
    "author": "Arthur C. Clarke",
    "description": "A thought-provoking comparison between advanced technology and magic."
  },
  {
    "id": 76,
    "category": "Creativity",
    "quote": "Creativity is intelligence having fun.",
    "author": "Albert Einstein",
    "description": "A playful definition of the relationship between creativity and intelligence."
  },
  {
    "id": 77,
    "category": "Courage",
    "quote": "It takes a great deal of bravery to stand up to our enemies, but just as much to stand up to our friends.",
    "author": "J.K. Rowling",
    "description": "Reflection on the various forms of courage, both in confrontation and support."
  },
  {
    "id": 78,
    "category": "Nature",
    "quote": "Look deep into nature, and then you will understand everything better.",
    "author": "Albert Einstein",
    "description": "Insight into the profound understanding that nature can offer about life and existence."
  },
  {
    "id": 79,
    "category": "Change",
    "quote": "Be the change that you wish to see in the world.",
    "author": "Mahatma Gandhi",
    "description": "A call to action for individuals to initiate positive change in the world."
  },
  {
    "id": 80,
    "category": "Wisdom",
    "quote": "Wisdom begins in wonder.",
    "author": "Socrates",
    "description": "A concise perspective on the origin of wisdom and the importance of curiosity."
  },
  {
    "id": 81,
    "category": "Inspiration",
    "quote": "The best way to predict the future is to create it.",
    "author": "Peter Drucker",
    "description": "An empowering quote encouraging proactive efforts in shaping one's future."
  },
  {
    "id": 82,
    "category": "Leadership",
    "quote": "A leader is one who knows the way, goes the way, and shows the way.",
    "author": "John C. Maxwell",
    "description": "A concise definition of leadership emphasizing knowledge, action, and guidance."
  },
  {
    "id": 83,
    "category": "Wisdom",
    "quote": "Knowing others is intelligence; knowing yourself is true wisdom. Mastering others is strength; mastering yourself is true power.",
    "author": "Lao Tzu",
    "description": "Insight into the facets of intelligence, wisdom, strength, and true power."
  },
  {
    "id": 84,
    "category": "Happiness",
    "quote": "The greatest happiness you can give is to be unwaveringly loyal to what you believe in.",
    "author": "Julie Donner Andersen",
    "description": "A perspective on the joy derived from unwavering loyalty to one's beliefs."
  },
  {
    "id": 85,
    "category": "Perseverance",
    "quote": "Success is not final, failure is not fatal: It is the courage to continue that counts.",
    "author": "Winston Churchill",
    "description": "A timeless reflection on the nature of success and courage in the face of challenges."
  },
  {
    "id": 86,
    "category": "Imagination",
    "quote": "The true sign of intelligence is not knowledge but imagination.",
    "author": "Albert Einstein",
    "description": "Einstein's viewpoint on the role of imagination in measuring intelligence."
  },
  {
    "id": 87,
    "category": "Hope",
    "quote": "Hope is important because it can make the present moment less difficult to bear. If we believe that tomorrow will be better, we can bear a hardship today.",
    "author": "Thich Nhat Hanh",
    "description": "A Buddhist perspective on the significance of hope in facing challenges."
  },
  {
    "id": 88,
    "category": "Friendship",
    "quote": "A friend is someone who knows all about you and still loves you.",
    "author": "Elbert Hubbard",
    "description": "A warm definition of the depth of true friendship."
  },
  {
    "id": 89,
    "category": "Courage",
    "quote": "Courage is not the absence of fear, but rather the assessment that something else is more important than fear.",
    "author": "Franklin D. Roosevelt",
    "description": "A nuanced perspective on the relationship between courage and fear."
  },
  {
    "id": 90,
    "category": "Wisdom",
    "quote": "Wisdom begins in wonder.",
    "author": "Socrates",
    "description": "A concise perspective on the origin of wisdom and the importance of curiosity."
  },
  {
    "id": 91,
    "category": "Motivation",
    "quote": "The only way to do great work is to love what you do.",
    "author": "Steve Jobs",
    "description": "An inspiring quote emphasizing the importance of passion in one's work."
  },
  {
    "id": 92,
    "category": "Life",
    "quote": "Life is what happens when you're busy making other plans.",
    "author": "John Lennon",
    "description": "A reminder to cherish the present moment amidst life's plans and uncertainties."
  },
  {
    "id": 93,
    "category": "Wisdom",
    "quote": "The only true wisdom is in knowing you know nothing.",
    "author": "Socrates",
    "description": "A philosophical insight into the nature of true wisdom and humility."
  },
  {
    "id": 94,
    "category": "Love",
    "quote": "The greatest happiness you can have is knowing that you do not necessarily require happiness.",
    "author": "William Saroyan",
    "description": "A unique perspective on finding happiness in not necessarily seeking it."
  },
  {
    "id": 95,
    "category": "Technology",
    "quote": "Any sufficiently advanced technology is indistinguishable from magic.",
    "author": "Arthur C. Clarke",
    "description": "A thought-provoking comparison between advanced technology and magic."
  },
  {
    "id": 96,
    "category": "Creativity",
    "quote": "Creativity is intelligence having fun.",
    "author": "Albert Einstein",
    "description": "A playful definition of the relationship between creativity and intelligence."
  },
  {
    "id": 97,
    "category": "Courage",
    "quote": "It takes a great deal of bravery to stand up to our enemies, but just as much to stand up to our friends.",
    "author": "J.K. Rowling",
    "description": "Reflection on the various forms of courage, both in confrontation and support."
  },
  {
    "id": 98,
    "category": "Nature",
    "quote": "Look deep into nature, and then you will understand everything better.",
    "author": "Albert Einstein",
    "description": "Insight into the profound understanding that nature can offer about life and existence."
  },
  {
    "id": 99,
    "category": "Change",
    "quote": "Be the change that you wish to see in the world.",
    "author": "Mahatma Gandhi",
    "description": "A call to action for individuals to initiate positive change in the world."
  },
  {
    "id": 100,
    "category": "Wisdom",
    "quote": "Wisdom begins in wonder.",
    "author": "Socrates",
    "description": "A concise perspective on the origin of wisdom and the importance of curiosity."
  },
  {
    "id": 101,
    "category": "Inspiration",
    "quote": "The best way to predict the future is to create it.",
    "author": "Peter Drucker",
    "description": "An empowering quote encouraging proactive efforts in shaping one's future."
  },
  {
    "id": 102,
    "category": "Leadership",
    "quote": "A leader is one who knows the way, goes the way, and shows the way.",
    "author": "John C. Maxwell",
    "description": "A concise definition of leadership emphasizing knowledge, action, and guidance."
  },
  {
    "id": 103,
    "category": "Wisdom",
    "quote": "Knowing others is intelligence; knowing yourself is true wisdom. Mastering others is strength; mastering yourself is true power.",
    "author": "Lao Tzu",
    "description": "Insight into the facets of intelligence, wisdom, strength, and true power."
  },
  {
    "id": 104,
    "category": "Happiness",
    "quote": "The greatest happiness you can give is to be unwaveringly loyal to what you believe in.",
    "author": "Julie Donner Andersen",
    "description": "A perspective on the joy derived from unwavering loyalty to one's beliefs."
  },
  {
    "id": 105,
    "category": "Perseverance",
    "quote": "Success is not final, failure is not fatal: It is the courage to continue that counts.",
    "author": "Winston Churchill",
    "description": "A timeless reflection on the nature of success and courage in the face of challenges."
  },
  {
    "id": 106,
    "category": "Imagination",
    "quote": "The true sign of intelligence is not knowledge but imagination.",
    "author": "Albert Einstein",
    "description": "Einstein's viewpoint on the role of imagination in measuring intelligence."
  },
  {
    "id": 107,
    "category": "Hope",
    "quote": "Hope is important because it can make the present moment less difficult to bear. If we believe that tomorrow will be better, we can bear a hardship today.",
    "author": "Thich Nhat Hanh",
    "description": "A Buddhist perspective on the significance of hope in facing challenges."
  },
  {
    "id": 108,
    "category": "Friendship",
    "quote": "A friend is someone who knows all about you and still loves you.",
    "author": "Elbert Hubbard",
    "description": "A warm definition of the depth of true friendship."
  },
  {
    "id": 109,
    "category": "Courage",
    "quote": "Courage is not the absence of fear, but rather the assessment that something else is more important than fear.",
    "author": "Franklin D. Roosevelt",
    "description": "A nuanced perspective on the relationship between courage and fear."
  },
  {
    "id": 110,
    "category": "Wisdom",
    "quote": "Wisdom begins in wonder.",
    "author": "Socrates",
    "description": "A concise perspective on the origin of wisdom and the importance of curiosity."
  },
  {
    "id": 111,
    "category": "Motivation",
    "quote": "The only way to do great work is to love what you do.",
    "author": "Steve Jobs",
    "description": "An inspiring quote emphasizing the importance of passion in one's work."
  },
  {
    "id": 112,
    "category": "Life",
    "quote": "Life is what happens when you're busy making other plans.",
    "author": "John Lennon",
    "description": "A reminder to cherish the present moment amidst life's plans and uncertainties."
  },
  {
    "id": 113,
    "category": "Wisdom",
    "quote": "The only true wisdom is in knowing you know nothing.",
    "author": "Socrates",
    "description": "A philosophical insight into the nature of true wisdom and humility."
  },
  {
    "id": 114,
    "category": "Love",
    "quote": "The greatest happiness you can have is knowing that you do not necessarily require happiness.",
    "author": "William Saroyan",
    "description": "A unique perspective on finding happiness in not necessarily seeking it."
  },
  {
    "id": 115,
    "category": "Technology",
    "quote": "Any sufficiently advanced technology is indistinguishable from magic.",
    "author": "Arthur C. Clarke",
    "description": "A thought-provoking comparison between advanced technology and magic."
  },
  {
    "id": 116,
    "category": "Creativity",
    "quote": "Creativity is intelligence having fun.",
    "author": "Albert Einstein",
    "description": "A playful definition of the relationship between creativity and intelligence."
  },
  {
    "id": 117,
    "category": "Courage",
    "quote": "It takes a great deal of bravery to stand up to our enemies, but just as much to stand up to our friends.",
    "author": "J.K. Rowling",
    "description": "Reflection on the various forms of courage, both in confrontation and support."
  },
  {
    "id": 118,
    "category": "Nature",
    "quote": "Look deep into nature, and then you will understand everything better.",
    "author": "Albert Einstein",
    "description": "Insight into the profound understanding that nature can offer about life and existence."
  },
  {
    "id": 119,
    "category": "Change",
    "quote": "Be the change that you wish to see in the world.",
    "author": "Mahatma Gandhi",
    "description": "A call to action for individuals to initiate positive change in the world."
  },
  {
    "id": 120,
    "category": "Wisdom",
    "quote": "Wisdom begins in wonder.",
    "author": "Socrates",
    "description": "A concise perspective on the origin of wisdom and the importance of curiosity."
  }
]